hs_api/__init__.py
hs_api/_intermediate_format.py
hs_api/_simple_sim.py
hs_api/api.py
hs_api/converter.py
hs_api-0.1.7.dist-info/METADATA
hs_api-0.1.7.dist-info/WHEEL
hs_api-0.1.7.dist-info/RECORD
