Metadata-Version: 2.1
Name: hs-api
Version: 0.1.7
Summary: CRI User Software
Author: Justin Frank & Abhinav Uppal
Requires-Python: >=3.10,<3.11
Classifier: Programming Language :: Python :: 3
Classifier: Programming Language :: Python :: 3.10
Requires-Dist: PyYAML (>=6.0,<7.0)
Requires-Dist: bidict (>=0.22.0,<0.23.0)
Requires-Dist: connectome-utils (>=0.1.0,<0.2.0)
Requires-Dist: fxpmath (>=0.4.8,<0.5.0)
Requires-Dist: matplotlib (>=3.5.1,<4.0.0)
Requires-Dist: numba (>=0.55.1,<0.56.0)
Requires-Dist: numpy (>=1.18)
Requires-Dist: tqdm (>=4.64.1,<5.0.0)
